pycolor/__init__.py
pycolor/__main__.py
pycolor/arguments.py
pycolor/config/__init__.py
pycolor/config/argpattern.py
pycolor/config/fromprofile.py
pycolor/config/pattern.py
pycolor/config/profile.py
pycolor/config/sample-config/aws_s3_sync.json
pycolor/config/sample-config/blkid.json
pycolor/config/sample-config/df.json
pycolor/config/sample-config/free.json
pycolor/config/sample-config/ifconfig.json
pycolor/config/sample-config/ping-unix.json
pycolor/config/sample-config/ping-windows.json
pycolor/config/sample-config/pip.json
pycolor/config/sample-config/pylint.json
pycolor/config/sample-config/rclone.json
pycolor/config/sample-config/rsync.json
pycolor/config/sample-config/zip.json
pycolor/config/schema/argpattern.json
pycolor/config/schema/fromprofile.json
pycolor/config/schema/pattern.json
pycolor/config/schema/profile.json
pycolor/execute/__init__.py
pycolor/execute/execute.py
pycolor/execute/threadwait.py
pycolor/pycolor/__init__.py
pycolor/pycolor/applypattern.py
pycolor/pycolor/profileloader.py
pycolor/pycolor/pycolor_class.py
pycolor/pycolor/pyformat/__init__.py
pycolor/pycolor/pyformat/context.py
pycolor/pycolor/pyformat/fieldsep.py
pycolor/pycolor/pyformat/coloring/__init__.py
pycolor/pycolor/pyformat/coloring/color.py
pycolor/pycolor/pyformat/coloring/colorpositions.py
pycolor/pycolor/pyformat/coloring/colorstate.py
pycolor/strman/__init__.py
pycolor/strman/match_group_replace.py
pycolor/strman/search_replace.py
pycolor/strman/split.py
pycolor/utils/__init__.py
pycolor/utils/debug_colors.py
pycolor/utils/group_index.py
pycolor/utils/printmsg.py
pycolor_term-0.1.0.dist-info/LICENSE
pycolor_term-0.1.0.dist-info/METADATA
pycolor_term-0.1.0.dist-info/WHEEL
pycolor_term-0.1.0.dist-info/entry_points.txt
pycolor_term-0.1.0.dist-info/top_level.txt
pycolor_term-0.1.0.dist-info/RECORD
