Metadata-Version: 2.1
Name: pycolor-term
Version: 0.1.0
Summary: Execute commands, coloring terminal output in real-time using ANSI color codes.
Home-page: https://github.com/WiLGYSeF/pycolor
Author: wilgysef
Author-email: wilgysef@gmail.com
License: UNKNOWN
Project-URL: Bug Tracker, https://github.com/WiLGYSeF/pycolor/issues
Platform: UNKNOWN
Classifier: Programming Language :: Python :: 3
Classifier: License :: OSI Approved :: MIT License
Classifier: Operating System :: OS Independent
Requires-Python: >=3.6
License-File: LICENSE
Requires-Dist: fastjsonschema
